LICENSE
MANIFEST.in
README.rst
setup.py
helpers/__init__.py
helpers/compose.py
helpers/config_manager.py
helpers/extend.py
helpers/logo.py
helpers/print_versions.py
helpers/ui.py
helpers/update.py
helpers/worklist.py
reactjo/__init__.py
reactjo/__main__.py
reactjo/reactjo.py
reactjo.egg-info/PKG-INFO
reactjo.egg-info/SOURCES.txt
reactjo.egg-info/dependency_links.txt
reactjo.egg-info/entry_points.txt
reactjo.egg-info/requires.txt
reactjo.egg-info/top_level.txt