Metadata-Version: 1.0
Name: reactjo
Version: 2.3.5
Summary: Extensible scaffolding engine.
Home-page: https://github.com/aaron-price/reactjo.git
Author: Aaron Price
Author-email: coding.aaronp@gmail.com
License: UNKNOWN
Platform: UNKNOWN
